[
  {
    "code": "12.01.09.1001",
    "value": "Sosor Gadong"
  },
  {
    "code": "12.01.09.2002",
    "value": "Unte Boang"
  },
  {
    "code": "12.01.09.2003",
    "value": "Sibintang"
  },
  {
    "code": "12.01.09.2004",
    "value": "Barambang"
  },
  {
    "code": "12.01.09.2005",
    "value": "Siantar Ca"
  },
  {
    "code": "12.01.09.2006",
    "value": "Muara Bolak"
  },
  {
    "code": "12.01.09.2007",
    "value": "Huta Tombak"
  },
  {
    "code": "12.01.09.2008",
    "value": "Siantar Dolok"
  },
  {
    "code": "12.01.09.2009",
    "value": "Baringin"
  }
]