[
  {
    "code": "12.72.02.1001",
    "value": "Dwikora"
  },
  {
    "code": "12.72.02.1002",
    "value": "Proklamasi"
  },
  {
    "code": "12.72.02.1003",
    "value": "Bantan"
  },
  {
    "code": "12.72.02.1004",
    "value": "Timbang Galung"
  },
  {
    "code": "12.72.02.1005",
    "value": "Simarito"
  },
  {
    "code": "12.72.02.1006",
    "value": "Sipinggolpinggol"
  },
  {
    "code": "12.72.02.1007",
    "value": "Banjar"
  },
  {
    "code": "12.72.02.1008",
    "value": "Teladan"
  }
]