[
  {
    "code": "15.01.07.2004",
    "value": "Tarutung"
  },
  {
    "code": "15.01.07.2006",
    "value": "Lubuk Paku"
  },
  {
    "code": "15.01.07.2007",
    "value": "Tamiai"
  },
  {
    "code": "15.01.07.2008",
    "value": "Pematang Lingkung"
  },
  {
    "code": "15.01.07.2009",
    "value": "Pasar Tamiai"
  },
  {
    "code": "15.01.07.2010",
    "value": "Seberang Merangin"
  },
  {
    "code": "15.01.07.2011",
    "value": "Baru Pulau Sangkar"
  },
  {
    "code": "15.01.07.2013",
    "value": "Batang Merangin"
  },
  {
    "code": "15.01.07.2014",
    "value": "Muara Hemat"
  }
]