[
  {
    "code": "17.02.09.1012",
    "value": "Dwi Tunggal"
  },
  {
    "code": "17.02.09.1013",
    "value": "Air Putih Lama"
  },
  {
    "code": "17.02.09.1023",
    "value": "Adirejo"
  },
  {
    "code": "17.02.09.1025",
    "value": "Air Rambai"
  },
  {
    "code": "17.02.09.1026",
    "value": "Pasar Baru"
  },
  {
    "code": "17.02.09.1027",
    "value": "Pasar Tengah"
  },
  {
    "code": "17.02.09.1031",
    "value": "Jalan Baru"
  },
  {
    "code": "17.02.09.1033",
    "value": "Talang Benih"
  },
  {
    "code": "17.02.09.1047",
    "value": "Timbul Rejo"
  }
]