[
  {
    "code": "19.04.06.2001",
    "value": "Perlang"
  },
  {
    "code": "19.04.06.2002",
    "value": "Batu Beriga"
  },
  {
    "code": "19.04.06.2003",
    "value": "Lubuk Besar"
  },
  {
    "code": "19.04.06.2004",
    "value": "Kulur"
  },
  {
    "code": "19.04.06.2005",
    "value": "Lubuk Lingkuk"
  },
  {
    "code": "19.04.06.2006",
    "value": "Lubuk Pabrik"
  },
  {
    "code": "19.04.06.2007",
    "value": "Trubus"
  },
  {
    "code": "19.04.06.2008",
    "value": "Kulur Ilir"
  },
  {
    "code": "19.04.06.2009",
    "value": "Belimbing"
  }
]