[
  {
    "code": "33.20.07.2001",
    "value": "Mororejo"
  },
  {
    "code": "33.20.07.2009",
    "value": "Suwawal"
  },
  {
    "code": "33.20.07.2010",
    "value": "Sinanggul"
  },
  {
    "code": "33.20.07.2011",
    "value": "Jambu"
  },
  {
    "code": "33.20.07.2012",
    "value": "Srobyong"
  },
  {
    "code": "33.20.07.2013",
    "value": "Sekuro"
  },
  {
    "code": "33.20.07.2014",
    "value": "Karanggondang"
  },
  {
    "code": "33.20.07.2015",
    "value": "Jambu Timur"
  }
]