[
  {
    "code": "63.07.11.2001",
    "value": "Tapuk"
  },
  {
    "code": "63.07.11.2002",
    "value": "Karau"
  },
  {
    "code": "63.07.11.2003",
    "value": "Limpasu"
  },
  {
    "code": "63.07.11.2004",
    "value": "Kabang"
  },
  {
    "code": "63.07.11.2005",
    "value": "Abung Surapati"
  },
  {
    "code": "63.07.11.2006",
    "value": "Karatungan"
  },
  {
    "code": "63.07.11.2007",
    "value": "Pauh"
  },
  {
    "code": "63.07.11.2008",
    "value": "Abung"
  },
  {
    "code": "63.07.11.2009",
    "value": "Hawang"
  }
]