[
  {
    "code": "65.02.13.2001",
    "value": "Setulang"
  },
  {
    "code": "65.02.13.2002",
    "value": "Setarap"
  },
  {
    "code": "65.02.13.2003",
    "value": "Punan Setarap"
  },
  {
    "code": "65.02.13.2004",
    "value": "Batu Kajang"
  },
  {
    "code": "65.02.13.2005",
    "value": "Gong Solok"
  },
  {
    "code": "65.02.13.2006",
    "value": "Punan Gong Solok"
  },
  {
    "code": "65.02.13.2007",
    "value": "Long Adiu"
  },
  {
    "code": "65.02.13.2008",
    "value": "Punan Long Adiu"
  }
]