[
  {
    "code": "95.04.06.2001",
    "value": "Wurineri"
  },
  {
    "code": "95.04.06.2002",
    "value": "Pokegi"
  },
  {
    "code": "95.04.06.2003",
    "value": "Arombok"
  },
  {
    "code": "95.04.06.2004",
    "value": "Enanagi"
  },
  {
    "code": "95.04.06.2005",
    "value": "Pindak"
  },
  {
    "code": "95.04.06.2006",
    "value": "Gilopaga"
  },
  {
    "code": "95.04.06.2007",
    "value": "Keribaga"
  },
  {
    "code": "95.04.06.2008",
    "value": "Wona"
  },
  {
    "code": "95.04.06.2009",
    "value": "Numbuboton"
  }
]