[
  {
    "code": "17.07.01",
    "value": "Lebong Utara"
  },
  {
    "code": "17.07.02",
    "value": "Lebong Atas"
  },
  {
    "code": "17.07.03",
    "value": "Lebong Tengah"
  },
  {
    "code": "17.07.04",
    "value": "Lebong Selatan"
  },
  {
    "code": "17.07.05",
    "value": "Rimbo Pengadang"
  },
  {
    "code": "17.07.06",
    "value": "Topos"
  },
  {
    "code": "17.07.07",
    "value": "Bingin Kuning"
  },
  {
    "code": "17.07.08",
    "value": "Lebong Sakti"
  },
  {
    "code": "17.07.09",
    "value": "Tubei"
  },
  {
    "code": "17.07.10",
    "value": "Amen"
  },
  {
    "code": "17.07.11",
    "value": "Uram Jaya"
  },
  {
    "code": "17.07.12",
    "value": "Pinang Belapis"
  }
]