[
  {
    "code": "18.10.01",
    "value": "Pringsewu"
  },
  {
    "code": "18.10.02",
    "value": "Gading Rejo"
  },
  {
    "code": "18.10.03",
    "value": "Ambarawa"
  },
  {
    "code": "18.10.04",
    "value": "Pardasuka"
  },
  {
    "code": "18.10.05",
    "value": "Pagelaran"
  },
  {
    "code": "18.10.06",
    "value": "Banyumas"
  },
  {
    "code": "18.10.07",
    "value": "Adiluwih"
  },
  {
    "code": "18.10.08",
    "value": "Sukoharjo"
  },
  {
    "code": "18.10.09",
    "value": "Pagelaran Utara"
  }
]