[
  {
    "code": "53.11.01",
    "value": "Kota Waingapu"
  },
  {
    "code": "53.11.02",
    "value": "Haharu"
  },
  {
    "code": "53.11.03",
    "value": "Lewa"
  },
  {
    "code": "53.11.04",
    "value": "Nggaha Ori Angu"
  },
  {
    "code": "53.11.05",
    "value": "Tabundung"
  },
  {
    "code": "53.11.06",
    "value": "Pinu Pahar"
  },
  {
    "code": "53.11.07",
    "value": "Pandawai"
  },
  {
    "code": "53.11.08",
    "value": "Umalulu"
  },
  {
    "code": "53.11.09",
    "value": "Rindi"
  },
  {
    "code": "53.11.10",
    "value": "Pahunga Lodu"
  },
  {
    "code": "53.11.11",
    "value": "Wulla Waijelu"
  },
  {
    "code": "53.11.12",
    "value": "Paberiwai"
  },
  {
    "code": "53.11.13",
    "value": "Karera"
  },
  {
    "code": "53.11.14",
    "value": "Kahaungu Eti"
  },
  {
    "code": "53.11.15",
    "value": "Matawai La Pawu"
  },
  {
    "code": "53.11.16",
    "value": "Kambera"
  },
  {
    "code": "53.11.17",
    "value": "Kambata Mapambuhang"
  },
  {
    "code": "53.11.18",
    "value": "Lewa Tidahu"
  },
  {
    "code": "53.11.19",
    "value": "Katala Hamu Lingu"
  },
  {
    "code": "53.11.20",
    "value": "Kanatang"
  },
  {
    "code": "53.11.21",
    "value": "Ngadu Ngala"
  },
  {
    "code": "53.11.22",
    "value": "Mahu"
  }
]